stcflash/__init__.py
stcflash/__main__.py
stcflash/frontend.py
stcflash/ihex.py
stcflash/models.py
stcflash/options.py
stcflash/protocols.py
stcflash/utils.py
stcflash-0.10.dist-info/METADATA
stcflash-0.10.dist-info/WHEEL
stcflash-0.10.dist-info/entry_points.txt
stcflash-0.10.dist-info/top_level.txt
stcflash-0.10.dist-info/RECORD
